nonebot_plugin_charpic/__init__.py
nonebot_plugin_charpic/adapter.py
nonebot_plugin_charpic/data_source.py
nonebot_plugin_charpic/font/consola.ttf
nonebot_plugin_charpic_migang-0.0.1.dist-info/METADATA
nonebot_plugin_charpic_migang-0.0.1.dist-info/WHEEL
nonebot_plugin_charpic_migang-0.0.1.dist-info/licenses/LICENSE
nonebot_plugin_charpic_migang-0.0.1.dist-info/RECORD
