Metadata-Version: 2.1
Name: nonebot-plugin-charpic-migang
Version: 0.0.1
Summary: Generate picture(or GIF) by characters
Author-Email: 1umine <a1628420979@163.com>
License: MIT
Requires-Python: >=3.10
Requires-Dist: Pillow>=10.0.0
Requires-Dist: aiohttp<4.0,>=3.8.0
Requires-Dist: imageio<3.0,>=2.9.0
Requires-Dist: nonebot2<3.0,>=2.0
Requires-Dist: nonebot-adapter-onebot<3.0,>=2.0
